Workbook

Sheet README
A1: FLEXO CYLINDER SELECTION, COSTING & PRICING SYSTEM
A3: SYSTEM GUIDE
A4: Purpose | B4: Integrated workbook for selecting the best printing cylinder/repeat, calculating web consumption, estimating machine cost, depreciation, and job selling price.
A5: Workflow | B5: 1) Enter job dimensions and quantity in JOB_INPUTS. 2) Review compatible cylinder options in CYLINDER_SELECTOR. 3) Confirm production assumptions. 4) Enter machine and cost parameters in MACHINE_COST. 5) Review total cost and selling price in JOB_COSTING.
A6: Yellow cells | B6: Manual inputs / assumptions.
A7: Green cells | B7: Calculated outputs.
A8: Cylinder logic | B8: Candidate repeat = cylinder teeth × 3.175 mm. The system calculates labels-around, actual gap, repeat utilization and ranks compatible cylinders.
A9: Important | B9: The current source file mixes manual inputs, formulas and pricing assumptions in one sheet. This rebuild separates master data, engineering calculations and costing to reduce errors.

Sheet MACHINE_COST
A1: MACHINE HOURLY COST & DEPRECIATION
A3: CAPEX & DEPRECIATION INPUTS
A4: Flexo Press Purchase Value | B4: 16000000 | C4: EGP
A5: Press Residual Value | B5: 0 | C5: EGP
A6: Press Useful Life | B6: 3 | C6: years
A7: Press Annual Operating Hours | B7: 5000 | C7: hours
A8: Inspection Machine Purchase Value | B8: 1200000 | C8: EGP
A9: Inspection Machine Residual Value | B9: 0 | C9: EGP
A10: Inspection Machine Useful Life | B10: 3 | C10: years
A11: Inspection Annual Operating Hours | B11: 5000 | C11: hours
A12: Slitting / Rewinding Machine Purchase Value | B12: 600000 | C12: EGP
A13: Slitting Machine Residual Value | B13: 0 | C13: EGP
A14: Slitting Machine Useful Life | B14: 3 | C14: years
A15: Slitting Annual Operating Hours | B15: 5000 | C15: hours
A18: OPERATING COST INPUTS
A19: Flexo Power Consumption | B19: 70 | C19: kW average
A20: Inspection Power Consumption | B20: 60 | C20: kW average
A21: Slitting Power Consumption | B21: 60 | C21: kW average
A22: Electricity Tariff | B22: 4 | C22: EGP/kWh
A23: Flexo Operators | B23: 6 | C23: persons
A24: Average Operator Cost / Hour | B24: 200 | C24: EGP/hour
A25: Maintenance Cost / Hour | B25: 150 | C25: EGP/hour
A26: Factory Overhead / Hour | B26: 100 | C26: EGP/hour
A27: Planned Utilization / Efficiency | B27: 85 | C27: %
A29: CALCULATED HOURLY COST
A30: Flexo Depreciation / Hour | B30: =IFERROR((B4-B5)/(B6*B7),0) -> 1066.666667
A31: Inspection Depreciation / Hour | B31: =IFERROR((B8-B9)/(B10*B11),0) -> 80
A32: Slitting Depreciation / Hour | B32: =IFERROR((B12-B13)/(B14*B15),0) -> 40
A33: Total Depreciation / Hour | B33: =SUM(B30:B32) -> 1186.666667
A34: Electricity / Hour | B34: =(B19+B20+B21)*B22 -> 760
A35: Labor / Hour | B35: =B23*B24 -> 1200
A36: Maintenance / Hour | B36: =B25 -> 150
A37: Factory Overhead / Hour | B37: =B26 -> 100
A38: Base Hourly Cost | B38: =SUM(B33:B37) -> 3396.666667
A39: Effective Hourly Cost | B39: =IFERROR(B38/(B27/100),0) -> 3996.078431

Sheet JOB_INPUTS
A1: JOB INPUTS
A3: JOB & PRODUCTION PARAMETERS
A4: Job ID | B4: JOB-001
A5: Customer
A6: Order Quantity (labels) | B6: 300000 | C6: pcs
A7: Required Label Per Roll | B7: 2000 | C7: pcs
A8: Required Rolls | B8: 2000 | C8: label/core
A9: Label Width | B9: 58 | C9: mm
A10: Label Length | B10: 90 | C10: mm
A11: Gap Across | B11: 3 | C11: mm
A12: Gap Around | B12: =+CYLINDER_SELECTOR!B24 -> 2.86875 | C12: mm
A13: Target Min Gap Around | B13: 2.5 | C13: mm
A14: Press Speed | B14: 70 | C14: m/min
A15: No. of Colors | B15: 7 | C15: colors
A16: Z Numper | B16: =CYLINDER_SELECTOR!B21 -> 117 | C16: =CYLINDER_SELECTOR!A4 -> Cylinder Teeth
A17: Repeat Across | B17: =B39 -> 5 | C17: Label
A18: Repeat around | B18: =CYLINDER_SELECTOR!B23 -> 4 | C18: Label
A19: Printing Plate Width | B19: =B41 -> 325 | C19: mm
A20: Printing Plate Length | B20: =CYLINDER_SELECTOR!B22 -> 371.475 | C20: mm
A21: Material Side Margin | B21: 10 | C21: mm
A22: Machine Width Limit | B22: 350 | C22: mm
A23: Setup Waste | B23: 70 | C23: m/color
A24: Roll Length | B24: 2000 | C24: m/roll
A25: Planned Waste % | B25: 10 | C25: %
A26: Rolls Required | B26: =JOB_COSTING!B15 -> 4 | C26: rolls
A27: Core Cost | B27: =C27/1200 -> 0.125 | C27: 150 | D27: EGP
A28: Carton Cost | B28: =C28*(B6/B7/5) -> 1050 | C28: 35 | D28: EGP
A29: Packaging Cost | B29: =(((B6/B7)/5)*30)+JOB_COSTING!B36 -> 3487.5 | D29: EGP
A30: Material Cost | B30: 25 | D30: EGP/m²
A31: Cold Foil Cost | B31: 18 | C31: =B31*JOB_COSTING!B17 -> 38723.12438 | D31: EGP | E31: 18
A32: Lamination Cost | B32: 2 | C32: =B32*JOB_COSTING!B17 -> 4302.569375 | D32: EGP | E32: 2
A33: Ink Cost / m² / Color | B33: 1 | C33: EGP/m²/color
A34: Other Direct Cost / Job (PREPRESS),(NEW DIECUTTER) | B34: 12000 | C34: EGP/job
A35: Target Profit Margin | B35: 50 | C35: %
A38: AUTOMATIC GEOMETRY
A39: No. Across | B39: =INT((B22-(2*B21))/(B9+B11)) -> 5 | C39: labels
A40: Used Print Width | B40: =B39*B9+(B39)*B11 -> 305 | C40: mm
A41: Material Width Required | B41: =B40+2*B21 -> 325 | C41: mm
A42: Fit Status | B42: =IF(B41<=B22,"FIT","CHECK WIDTH") -> FIT

Sheet JOB_COSTING
A1: JOB COSTING & SELLING PRICE | L1: JOB COSTING & SELLING PRICE
A3: PRODUCTION QUANTITY & MATERIAL CALCULATION | L3: PRODUCTION QUANTITY & MATERIAL CALCULATION IN DOUBLE LAYER LABEL
A4: Order Quantity | B4: =JOB_INPUTS!B6 -> 300,000 | C4: labels | L4: Order Quantity | M4: =B4/2 -> 150000 | N4: labels
A5: No. Across | B5: =JOB_INPUTS!B39 -> 5 | C5: labels | L5: No. Across | M5: =B5/2 -> 2.5 | N5: labels
A6: No. Around | B6: =CYLINDER_SELECTOR!B23 -> 4 | C6: labels | L6: Labels Around | M6: =B6 -> 4 | N6: labels
A7: Gap Around | B7: =CYLINDER_SELECTOR!B24 -> 2.86875 | C7: mm | L7: Gap Around | M7: =B7 -> 2.86875 | N7: m
A8: Labels per Repeat | B8: =B5*B6 -> 20 | C8: Label | L8: Labels per Repeat | M8: =M5*M6 -> 10 | N8: labels
A9: Cylinder Repeat | B9: =CYLINDER_SELECTOR!B22 -> 371.475 | C9: mm | L9: Cylinder Repeat | M9: =B9 -> 371.475 | N9: mm
A10: Net Web Length | B10: =IFERROR((B4/B8)*B9/1000,0) -> 5572.125 | C10: m | L10: Net Web Length | M10: =IFERROR((M4/M8)*M9/1000,0) -> 5572.125 | N10: m
A11: Setup Waste | B11: =JOB_INPUTS!B15*JOB_INPUTS!B23 -> 490 | C11: m | L11: Setup Waste | M11: =B11*2 -> 980 | N11: m
A12: Production Waste | B12: =B10*(JOB_INPUTS!B25/100) -> 557.2125 | C12: m | L12: Production Waste | M12: =B12*2 -> 1114.425 | N12: m
A13: Total Web Length | B13: =SUM(B10:B12) -> 6619.3375 | C13: m | L13: Total Web Length | M13: =SUM(M10:M12) -> 7666.55 | N13: m
A14: Roll Length | B14: =JOB_INPUTS!B24 -> 2000 | C14: m/roll | L14: Roll Length | M14: =B14 -> 2000 | N14: m/roll
A15: Rolls Required | B15: =ROUNDUP(B13/B14,0) -> 4 | C15: rolls | L15: Rolls Required | M15: =ROUNDUP(M13/M14,0) -> 4 | N15: rolls
A16: Material Width | B16: =JOB_INPUTS!B41 -> 325 | C16: mm | L16: Material Width | M16: =B16 -> 325 | N16: mm
A17: Material Area | B17: =B13*B16/1000 -> 2151.284688 | C17: m² | L17: Material Area | M17: =M13*M16/1000 -> 2491.62875 | N17: m²
A21: TIME CALCULATION | L21: TIME CALCULATION IN DOUBLE LAYER LABEL
A22: Flexo Running Time | B22: =IFERROR(B13/JOB_INPUTS!B14,0) -> 94.56196429 | C22: min | L22: Flexo Running Time | M22: =IFERROR(M13/JOB_INPUTS!B14,0) -> 109.5221429 | N22: min
A23: Setup Time | B23: 60 | C23: min | L23: Setup Time | M23: 60 | N23: min
A24: Total Flexo Time | B24: =(B22+B23)/60 -> 2.576032738 | C24: hours | L24: Total Flexo Time | M24: =(M22+M23)/60 -> 2.825369048 | N24: hours
A25: Inspection Time | B25: =(B13/70)/60 -> 1.576032738 | C25: hours | L25: Inspection Time | M25: =(M13/70)/60 -> 1.825369048 | N25: hours
A26: Slitting / Rewinding Time | B26: 0.5 | C26: hours | L26: Slitting / Rewinding Time | M26: 0.5 | N26: hours
A27: Total Machine Time | B27: =SUM(B24:B26) -> 4.652065476 | C27: hours | L27: Total Machine Time | M27: =SUM(M24:M26) -> 5.150738095 | N27: hours
A30: COST & SELLING PRICE | L30: COST & SELLING PRICE IN DOUBLE LAYER LABEL
A31: Material Cost | B31: =B17*JOB_INPUTS!B30 -> 53782.11719 | C31: EGP | L31: Material Cost | M31: =M17*JOB_INPUTS!B30 -> 62290.71875 | N31: EGP
A32: Ink Cost | B32: =B17*JOB_INPUTS!B33*JOB_INPUTS!B15 -> 15058.99281 | C32: EGP | E32: 240 ml eva | L32: Ink Cost | M32: =M17*JOB_INPUTS!B33*JOB_INPUTS!B15 -> 17441.40125 | N32: EGP
A33: Machine & Operating Cost | B33: =B27*MACHINE_COST!B39 -> 18590.01851 | C33: EGP | L33: Machine & Operating Cost | M33: =M27*MACHINE_COST!B39 -> 20582.75341 | N33: EGP
A34: Cold Foil Cost | B34: =JOB_INPUTS!C31 -> 38723.12438 | C34: EGP
A35: Lamination Cost | B35: =JOB_INPUTS!C32 -> 4302.569375 | C35: EGP
A36: Core Cost | B36: =(JOB_INPUTS!B6/JOB_INPUTS!B7)*((JOB_INPUTS!B9+80)*JOB_INPUTS!B27) -> 2587.5 | C36: EGP | L36: Core Cost | M36: =B36 -> 2587.5 | N36: EGP
A37: Carton Cost | B37: =35*(JOB_INPUTS!B6/JOB_INPUTS!B7/5) -> 1050 | C37: EGP | L37: Carton Cost | M37: =B37 -> 1050 | N37: EGP
A38: Plates Cost | B38: =JOB_INPUTS!B19*JOB_INPUTS!B20*JOB_INPUTS!B15*1*0.01 -> 8451.05625 | C38: EGP
A39: Other Direct Cost | B39: =JOB_INPUTS!B34 -> 12,000 | C39: EGP | L39: Other Direct Cost | M39: =JOB_INPUTS!B34 -> 12,000 | N39: EGP
A40: Total Job Cost | B40: =SUM(B31:B39) -> 154545.3785 | C40: EGP | L40: Total Job Cost | M40: =SUM(M31:M39) -> 115952.3734 | N40: EGP
A41: Cost / 1,000 Labels | B41: =IFERROR(B40/B4*1000,0) -> 515.1512617 | C41: EGP/1000 | L41: Cost / 1,000 Labels | M41: =IFERROR(M40/M4*1000,0) -> 773.0158227 | N41: EGP/1000
A42: Cost / Label | B42: =IFERROR(B40/B4,0) -> 0.5151512617 | C42: EGP | L42: Cost / Label | M42: =IFERROR(M40/M4,0) -> 0.7730158227 | N42: EGP
A43: Selling Price After Margin | B43: =IFERROR(B40/(1-JOB_INPUTS!B35/100),0) -> 309090.757 | C43: EGP | L43: Selling Price After Margin | M43: =IFERROR(M40/(1-JOB_INPUTS!B35/100),0) -> 231904.7468 | N43: EGP
A44: Selling Price / 1,000 Labels | B44: =IFERROR(B43/B4*1000,0) -> 1030.302523 | C44: EGP/1000 | L44: Selling Price / 1,000 Labels | M44: =IFERROR(M43/M4*1000,0) -> 1546.031645 | N44: EGP/1000
A45: Selling Price / Label | B45: =IFERROR(B43/B4,0) -> 1.030302523 | C45: EGP | L45: Selling Price / Label | M45: =IFERROR(M43/M4,0) -> 1.546031645 | N45: EGP
A46: Expected Profit | B46: =B43-B40 -> 154545.3785 | C46: EGP | L46: Expected Profit | M46: =M43-M40 -> 115952.3734 | N46: EGP
J61: 100000
J62: Total Job Cost | K62: 125748.66 | L62: EGP
J63: Cost / 1,000 Labels | K63: 1257.4866 | L63: EGP/1000
J65: Cost / Label | K65: 1.2574866 | L65: EGP
J66: 200000
J67: Total Job Cost | K67: 219706.38 | L67: EGP
J68: Cost / 1,000 Labels | K68: 1098.5319 | L68: EGP/1000
J69: Cost / Label | K69: 1.0985319 | L69: EGP
J70: 300000
J71: Total Job Cost | K71: 313664.1 | L71: EGP
J72: Cost / 1,000 Labels | K72: 1045.547 | L72: EGP/1000
J73: Cost / Label | K73: 1.045547 | L73: EGP
J76: 85ml Eva cosmatics
J77: 300000
J78: Total Job Cost | K78: 154545.38 | L78: EGP
J79: Cost / 1,000 Labels | K79: 515.15126 | L79: EGP/1000
J80: Cost / Label | K80: 0.51515126 | L80: EGP
J82: 200000
J83: Total Job Cost | K83: 114916.45 | L83: EGP
J84: Cost / 1,000 Labels | K84: 574.58225 | L84: EGP/1000
J85: Cost / Label | K85: 0.57458225 | L85: EGP
J87: 100000
J88: Total Job Cost | K88: 75287.521 | L88: EGP
J89: Cost / 1,000 Labels | K89: 752.87521 | L89: EGP/1000
J90: Cost / Label | K90: 0.75287521 | L90: EGP

Sheet ANALYSIS
A1: ANALYSIS OF ORIGINAL FILE & CONTROL POINTS
A3: MAIN FINDINGS
A4: 1 | B4: The original workbook combines job data, cylinder selection, material consumption and pricing assumptions on one REVISION sheet.
A5: 2 | B5: Cylinder selection is partly manual: a list of available tooth counts is tested against label length and a fixed minimum gap formula.
A6: 3 | B6: The source uses 3.175 mm per cylinder tooth, which is retained in the new selector.
A7: 4 | B7: Material width logic and repeat logic are separated from costing in the new system so changes to label dimensions update downstream calculations.
A8: 5 | B8: Original pricing formulas use assumptions such as 50 m setup allowance per color, 2,000 m roll length and a profit/markup calculation. These are now editable inputs.
A9: 6 | B9: Machine depreciation was not structurally separated. The new workbook calculates hourly depreciation for the flexo press, inspection machine and slitting/rewinding machine independently.
A10: 7 | B10: All zero-cost values in MACHINE_COST are intentionally editable because machine purchase values, energy tariff and labor costs must come from your actual factory figures.
A11: 8 | B11: Recommendation: validate the final selected cylinder against the actual press gear standard, plate thickness, mounting tape and OEM repeat chart before production.

Sheet CYLINDER_DB
A1: DIE CUTTER NORMAL & SPECIAL
A2: 84 | B2: Width | C2: Length | D2: Gap Across | E2: Gap Around | F2: NO.Across | G2: NO.Around | H2: Total no. | I2: Z No. | J2: Repeat | K2: Print Area Cm2 | L2: 1000/Sqm | M2: Material Width | N2: Material | O2: Order No. | P2: Notes
A3: 1 | B3: 100 | C3: 150 | D3: 3 | E3: =(J3/G3)-C3 -> 2.4 | F3: 4 | G3: 2 | H3: =G3*F3 -> 8 | I3: 96 | J3: =(I3/8)*25.4 -> 304.8 | K3: =M3*J3/100 -> 1307.592 | L3: =(1000/H3)*(J3/1000)*M3/1000 -> 16.3449 | M3: =( B3+D3)*F3+17 -> 429 | N3: Paper | O3: 013/001 | P3: 2 die cutter spilker & wink | R3: Paper
A4: 2 | B4: 50 | C4: 100 | D4: 3 | E4: =(J4/G4)-C4 -> 3.716666667 | F4: 7 | G4: 3 | H4: =G4*F4 -> 21 | I4: 98 | J4: =(I4/8)*25.4 -> 311.15 | K4: =M4*J4/100 -> 1207.262 | L4: =(1000/H4)*(J4/1000)*M4/1000 -> 5.748866667 | M4: =( B4+D4)*F4+17 -> 388 | N4: Paper | O4: 013/002 | P4: 1.2.3 SYRUP 120 GM | R4: Film
A5: 3 | B5: 45 | C5: 159 | D5: 3 | E5: =(J5/G5)-C5 -> 2.925 | F5: 8 | G5: 2 | H5: =G5*F5 -> 16 | I5: 102 | J5: =(I5/8)*25.4 -> 323.85 | K5: =M5*J5/100 -> 1298.6385 | L5: =(1000/H5)*(J5/1000)*M5/1000 -> 8.116490625 | M5: =( B5+D5)*F5+17 -> 401 | N5: Paper | O5: 013/003
A6: 4 | B6: 60 | C6: 159 | D6: 3 | E6: =(J6/G6)-C6 -> 2.925 | F6: 6 | G6: 2 | H6: =G6*F6 -> 12 | I6: 102 | J6: =(I6/8)*25.4 -> 323.85 | K6: =M6*J6/100 -> 1279.2075 | L6: =(1000/H6)*(J6/1000)*M6/1000 -> 10.6600625 | M6: =( B6+D6)*F6+17 -> 395 | N6: Paper | O6: 013/004
A7: 5 | B7: 100 | C7: 25 | D7: 3 | E7: =(J7/G7)-C7 -> 3.3765625 | F7: 4 | G7: 16 | H7: =G7*F7 -> 64 | I7: 143 | J7: =(I7/8)*25.4 -> 454.025 | K7: =M7*J7/100 -> 1947.76725 | L7: =(1000/H7)*(J7/1000)*M7/1000 -> 3.043386328 | M7: =( B7+D7)*F7+17 -> 429 | N7: Paper | O7: 013/005
A8: 6 | B8: 38 | C8: 25 | D8: 3 | E8: =(J8/G8)-C8 -> 3.3765625 | F8: 10 | G8: 16 | H8: =G8*F8 -> 160 | I8: 143 | J8: =(I8/8)*25.4 -> 454.025 | K8: =M8*J8/100 -> 1938.68675 | L8: =(1000/H8)*(J8/1000)*M8/1000 -> 1.211679219 | M8: =( B8+D8)*F8+17 -> 427 | N8: Paper | O8: 013/006
A9: 7 | B9: 140 | C9: 80 | D9: 3 | E9: =(J9/G9)-C9 -> 3.34375 | F9: 2 | G9: 4 | H9: =G9*F9 -> 8 | I9: 105 | J9: =(I9/8)*25.4 -> 333.375 | K9: =M9*J9/100 -> 1010.12625 | L9: =(1000/H9)*(J9/1000)*M9/1000 -> 12.62657813 | M9: =( B9+D9)*F9+17 -> 303 | N9: Paper | O9: 013/007 | P9: Arma - OXI 700
A10: 8 | B10: 30 | C10: 30 | D10: 3 | E10: =(J10/G10)-C10 -> 3.866666667 | F10: 12 | G10: 9 | H10: =G10*F10 -> 108 | I10: 96 | J10: =(I10/8)*25.4 -> 304.8 | K10: =M10*J10/100 -> 1258.824 | L10: =(1000/H10)*(J10/1000)*M10/1000 -> 1.165577778 | M10: =( B10+D10)*F10+17 -> 413 | N10: Paper | O10: 013/008
A11: 9 | B11: 202 | C11: 168 | D11: 3 | E11: =(J11/G11)-C11 -> 3.45 | F11: 1 | G11: 2 | H11: =G11*F11 -> 2 | I11: 108 | J11: =(I11/8)*25.4 -> 342.9 | K11: =M11*J11/100 -> 761.238 | L11: =(1000/H11)*(J11/1000)*M11/1000 -> 38.0619 | M11: =( B11+D11)*F11+17 -> 222 | N11: Paper | O11: 013/009 | P11: Arma - Wafer - cut the die to be 1 in width
A12: 10 | B12: 97 | C12: 72 | D12: 3 | E12: =(J12/G12)-C12 -> 4.2 | F12: 4 | G12: 4 | H12: =G12*F12 -> 16 | I12: 96 | J12: =(I12/8)*25.4 -> 304.8 | K12: =M12*J12/100 -> 1271.016 | L12: =(1000/H12)*(J12/1000)*M12/1000 -> 7.94385 | M12: =( B12+D12)*F12+17 -> 417 | N12: Film | O12: 013/010 | P12: Energy-DOT4
A13: 11 | B13: 190 | C13: 148 | D13: 3 | E13: =(J13/G13)-C13 -> 3.341666667 | F13: 2 | G13: 3 | H13: =G13*F13 -> 6 | I13: 143 | J13: =(I13/8)*25.4 -> 454.025 | K13: =M13*J13/100 -> 1829.72075 | L13: =(1000/H13)*(J13/1000)*M13/1000 -> 30.49534583 | M13: =( B13+D13)*F13+17 -> 403 | N13: Film | O13: 013/011 | P13: Energy - cool water
A14: 12 | B14: 240 | C14: 168 | D14: 3 | E14: =(J14/G14)-C14 -> 3.45 | F14: 1 | G14: 2 | H14: =G14*F14 -> 2 | I14: 108 | J14: =(I14/8)*25.4 -> 342.9 | K14: =M14*J14/100 -> 891.54 | L14: =(1000/H14)*(J14/1000)*M14/1000 -> 44.577 | M14: =( B14+D14)*F14+17 -> 260 | N14: Film | O14: 013/012 | P14: Al Rawda Sweet
A15: 13 | B15: 35 | C15: 35 | D15: 3 | E15: =(J15/G15)-C15 -> 3.1 | F15: 10 | G15: 8 | H15: =G15*F15 -> 80 | I15: 96 | J15: =(I15/8)*25.4 -> 304.8 | K15: =M15*J15/100 -> 1210.056 | L15: =(1000/H15)*(J15/1000)*M15/1000 -> 1.51257 | M15: =( B15+D15)*F15+17 -> 397 | N15: Paper | O15: 013/013
A16: 14 | B16: 124 | C16: 124 | D16: 3 | E16: =(J16/G16)-C16 -> 3 | F16: 3 | G16: 3 | H16: =G16*F16 -> 9 | I16: 120 | J16: =(I16/8)*25.4 -> 381 | K16: =M16*J16/100 -> 1516.38 | L16: =(1000/H16)*(J16/1000)*M16/1000 -> 16.84866667 | M16: =( B16+D16)*F16+17 -> 398 | N16: Paper | O16: 013/014
A17: 15 | B17: 165 | C17: 153 | D17: 3 | E17: =(J17/G17)-C17 -> 2.575 | F17: 2 | G17: 2 | H17: =G17*F17 -> 4 | I17: 98 | J17: =(I17/8)*25.4 -> 311.15 | K17: =M17*J17/100 -> 1098.3595 | L17: =(1000/H17)*(J17/1000)*M17/1000 -> 27.4589875 | M17: =( B17+D17)*F17+17 -> 353 | N17: Paper | O17: 013/015 | P17: Mobil (need to be film+lamination)
A18: 16 | B18: 70 | C18: 140 | D18: 3 | E18: =(J18/G18)-C18 -> 2.875 | F18: 5 | G18: 3 | H18: =G18*F18 -> 15 | I18: 135 | J18: =(I18/8)*25.4 -> 428.625 | K18: =M18*J18/100 -> 1637.3475 | L18: =(1000/H18)*(J18/1000)*M18/1000 -> 10.91565 | M18: =( B18+D18)*F18+17 -> 382 | N18: Paper | O18: 013/016
A19: 17 | B19: 50 | C19: 123 | D19: 3 | E19: =(J19/G19)-C19 -> 4 | F19: 7 | G19: 3 | H19: =G19*F19 -> 21 | I19: 120 | J19: =(I19/8)*25.4 -> 381 | K19: =M19*J19/100 -> 1478.28 | L19: =(1000/H19)*(J19/1000)*M19/1000 -> 7.039428571 | M19: =( B19+D19)*F19+17 -> 388 | N19: Paper | O19: 013/017
A20: 18 | B20: 145 | C20: 146 | D20: 3 | E20: =(J20/G20)-C20 -> 5.341666667 | F20: 2 | G20: 3 | H20: =G20*F20 -> 6 | I20: 143 | J20: =(I20/8)*25.4 -> 454.025 | K20: =M20*J20/100 -> 1421.09825 | L20: =(1000/H20)*(J20/1000)*M20/1000 -> 23.68497083 | M20: =( B20+D20)*F20+17 -> 313 | N20: Film | O20: 013/018 | P20: Tabco-front&back
A21: 19 | B21: 49 | C21: 140 | D21: 3 | E21: =(J21/G21)-C21 -> 2.875 | F21: 8 | G21: 3 | H21: =G21*F21 -> 24 | I21: 135 | J21: =(I21/8)*25.4 -> 428.625 | K21: =M21*J21/100 -> 1855.94625 | L21: =(1000/H21)*(J21/1000)*M21/1000 -> 7.733109375 | M21: =( B21+D21)*F21+17 -> 433 | N21: Paper | O21: 013/019
A22: 20 | B22: 65 | C22: 65 | D22: 3 | E22: =(J22/G22)-C22 -> 3.58 | F22: 6 | G22: 5 | H22: =G22*F22 -> 30 | I22: 108 | J22: =(I22/8)*25.4 -> 342.9 | K22: =M22*J22/100 -> 1457.325 | L22: =(1000/H22)*(J22/1000)*M22/1000 -> 4.85775 | M22: =( B22+D22)*F22+17 -> 425 | N22: Paper | O22: 013/020
A23: 21 | B23: 110 | C23: 57 | D23: 3 | E23: =(J23/G23)-C23 -> 3.96 | F23: 3 | G23: 5 | H23: =G23*F23 -> 15 | I23: 96 | J23: =(I23/8)*25.4 -> 304.8 | K23: =M23*J23/100 -> 1085.088 | L23: =(1000/H23)*(J23/1000)*M23/1000 -> 7.23392 | M23: =( B23+D23)*F23+17 -> 356 | N23: Film | O23: 013/021 | P23: Puerx
A24: 22 | B24: 134 | C24: 82 | D24: 3 | E24: =(J24/G24)-C24 -> 3.725 | F24: 2 | G24: 4 | H24: =G24*F24 -> 8 | I24: 108 | J24: =(I24/8)*25.4 -> 342.9 | K24: =M24*J24/100 -> 997.839 | L24: =(1000/H24)*(J24/1000)*M24/1000 -> 12.4729875 | M24: =( B24+D24)*F24+17 -> 291 | N24: Paper | O24: 013/022 | P24: Afia-Front&Back
A25: 23 | B25: 50 | C25: 50 | D25: 3 | E25: =(J25/G25)-C25 -> 3.578125 | F25: 7 | G25: 8 | H25: =G25*F25 -> 56 | I25: 135 | J25: =(I25/8)*25.4 -> 428.625 | K25: =M25*J25/100 -> 1663.065 | L25: =(1000/H25)*(J25/1000)*M25/1000 -> 2.969758929 | M25: =( B25+D25)*F25+17 -> 388 | N25: Paper | O25: 013/023 | P25: Afia-Hart
A26: 24 | B26: 70 | C26: 60 | D26: 3 | E26: =(J26/G26)-C26 -> 3.5 | F26: 5 | G26: 6 | H26: =G26*F26 -> 30 | I26: 120 | J26: =(I26/8)*25.4 -> 381 | K26: =M26*J26/100 -> 1455.42 | L26: =(1000/H26)*(J26/1000)*M26/1000 -> 4.8514 | M26: =( B26+D26)*F26+17 -> 382 | N26: Paper | O26: 013/024 | P26: Afia-Hart
A27: 25 | B27: 20 | C27: 124 | D27: 3 | E27: =(J27/G27)-C27 -> 3 | F27: 13 | G27: 3 | H27: =G27*F27 -> 39 | I27: 120 | J27: =(I27/8)*25.4 -> 381 | K27: =M27*J27/100 -> 1203.96 | L27: =(1000/H27)*(J27/1000)*M27/1000 -> 3.087076923 | M27: =( B27+D27)*F27+17 -> 316 | N27: Paper | O27: 013/025
A28: 26 | B28: 160 | C28: 64 | D28: 3 | E28: =(J28/G28)-C28 -> 2.675 | F28: 2 | G28: 5 | H28: =G28*F28 -> 10 | I28: 105 | J28: =(I28/8)*25.4 -> 333.375 | K28: =M28*J28/100 -> 1143.47625 | L28: =(1000/H28)*(J28/1000)*M28/1000 -> 11.4347625 | M28: =( B28+D28)*F28+17 -> 343 | N28: Film | O28: 013/026 | P28: Nefrtary -sparkel shampoo 400ml - F&B
A29: 27 | B29: 80 | C29: 124 | D29: 3 | E29: =(J29/G29)-C29 -> 3 | F29: 5 | G29: 3 | H29: =G29*F29 -> 15 | I29: 120 | J29: =(I29/8)*25.4 -> 381 | K29: =M29*J29/100 -> 1645.92 | L29: =(1000/H29)*(J29/1000)*M29/1000 -> 10.9728 | M29: =( B29+D29)*F29+17 -> 432 | N29: Paper | O29: 013/027
A30: 28 | B30: 102 | C30: 75 | D30: 3 | E30: =(J30/G30)-C30 -> 2.7875 | F30: 2 | G30: 4 | H30: =G30*F30 -> 8 | I30: 98 | J30: =(I30/8)*25.4 -> 311.15 | K30: =M30*J30/100 -> 706.3105 | L30: =(1000/H30)*(J30/1000)*M30/1000 -> 8.82888125 | M30: =( B30+D30)*F30+17 -> 227 | N30: Paper | O30: 013/028 | P30: My Way F&B 500 ml
A31: 29 | B31: 175 | C31: 111 | D31: 3 | E31: =(J31/G31)-C31 -> 3.3 | F31: 2 | G31: 3 | H31: =G31*F31 -> 6 | I31: 108 | J31: =(I31/8)*25.4 -> 342.9 | K31: =M31*J31/100 -> 1279.017 | L31: =(1000/H31)*(J31/1000)*M31/1000 -> 21.31695 | M31: =( B31+D31)*F31+17 -> 373 | N31: Paper | O31: 013/029 | P31: My Way F&B 1500 ml
A32: 30 | B32: 38 | C32: 25 | D32: 3 | E32: =(J32/G32)-C32 -> 2.709090909 | F32: 6 | G32: 11 | H32: =G32*F32 -> 66 | I32: 96 | J32: =(I32/8)*25.4 -> 304.8 | K32: =M32*J32/100 -> 801.624 | L32: =(1000/H32)*(J32/1000)*M32/1000 -> 1.214581818 | M32: =( B32+D32)*F32+17 -> 263 | N32: Paper | O32: 013/030 | P32: 38 X 25/2 without corner
A33: 31 | B33: 70 | C33: 148 | D33: 3 | E33: =(J33/G33)-C33 -> 4.4 | F33: 5 | G33: 2 | H33: =G33*F33 -> 10 | I33: 96 | J33: =(I33/8)*25.4 -> 304.8 | K33: =M33*J33/100 -> 1164.336 | L33: =(1000/H33)*(J33/1000)*M33/1000 -> 11.64336 | M33: =( B33+D33)*F33+17 -> 382 | N33: Paper | O33: 013/031 | P33: fefa olives
A34: 32 | B34: 55 | C34: 124 | D34: 3 | E34: =(J34/G34)-C34 -> 3 | F34: 7 | G34: 3 | H34: =G34*F34 -> 21 | I34: 120 | J34: =(I34/8)*25.4 -> 381 | K34: =M34*J34/100 -> 1611.63 | L34: =(1000/H34)*(J34/1000)*M34/1000 -> 7.674428571 | M34: =( B34+D34)*F34+17 -> 423 | N34: Paper | O34: 013/032
A35: 33 | B35: 50 | C35: 111 | D35: 3 | E35: =(J35/G35)-C35 -> 3.3 | F35: 7 | G35: 3 | H35: =G35*F35 -> 21 | I35: 108 | J35: =(I35/8)*25.4 -> 342.9 | K35: =M35*J35/100 -> 1330.452 | L35: =(1000/H35)*(J35/1000)*M35/1000 -> 6.335485714 | M35: =( B35+D35)*F35+17 -> 388 | N35: Paper | O35: 013/033
A36: 34 | B36: 150 | C36: 128 | D36: 3 | E36: =(J36/G36)-C36 -> 5.35 | F36: 2 | G36: 3 | H36: =G36*F36 -> 6 | I36: 126 | J36: =(I36/8)*25.4 -> 400.05 | K36: =M36*J36/100 -> 1292.1615 | L36: =(1000/H36)*(J36/1000)*M36/1000 -> 21.536025 | M36: =( B36+D36)*F36+17 -> 323 | N36: Film | O36: 013/034 | P36: Caltex valor 300 - 4 ltr
A37: 35 | B37: 140 | C37: 60 | D37: 3 | E37: =(J37/G37)-C37 -> 3.5 | F37: 2 | G37: 6 | H37: =G37*F37 -> 12 | I37: 120 | J37: =(I37/8)*25.4 -> 381 | K37: =M37*J37/100 -> 1154.43 | L37: =(1000/H37)*(J37/1000)*M37/1000 -> 9.62025 | M37: =( B37+D37)*F37+17 -> 303 | N37: Film | O37: 013/035
A38: 36 | B38: 55 | C38: 105 | D38: 3 | E38: =(J38/G38)-C38 -> 2.95 | F38: 7 | G38: 3 | H38: =G38*F38 -> 21 | I38: 102 | J38: =(I38/8)*25.4 -> 323.85 | K38: =M38*J38/100 -> 1369.8855 | L38: =(1000/H38)*(J38/1000)*M38/1000 -> 6.523264286 | M38: =( B38+D38)*F38+17 -> 423 | N38: Paper | O38: 013/036
A39: 37 | B39: 92.75 | C39: 100 | D39: 3 | E39: =(J39/G39)-C39 -> 3.716666667 | F39: 4 | G39: 3 | H39: =G39*F39 -> 12 | I39: 98 | J39: =(I39/8)*25.4 -> 311.15 | K39: =M39*J39/100 -> 1244.6 | L39: =(1000/H39)*(J39/1000)*M39/1000 -> 10.37166667 | M39: =( B39+D39)*F39+17 -> 400 | N39: Paper | O39: 013/037
A40: 38 | B40: 100 | C40: 92.75 | D40: 3 | E40: =(J40/G40)-C40 -> 2.5 | F40: 3 | G40: 4 | H40: =G40*F40 -> 12 | I40: 120 | J40: =(I40/8)*25.4 -> 381 | K40: =M40*J40/100 -> 1242.06 | L40: =(1000/H40)*(J40/1000)*M40/1000 -> 10.3505 | M40: =( B40+D40)*F40+17 -> 326 | N40: Paper | O40: 013/038
A41: 39 | B41: 65 | C41: 111 | D41: 3 | E41: =(J41/G41)-C41 -> 3.3 | F41: 6 | G41: 3 | H41: =G41*F41 -> 18 | I41: 108 | J41: =(I41/8)*25.4 -> 342.9 | K41: =M41*J41/100 -> 1457.325 | L41: =(1000/H41)*(J41/1000)*M41/1000 -> 8.09625 | M41: =( B41+D41)*F41+17 -> 425 | N41: Paper | O41: 013/039 | P41: WadiFood- Tometo 370 gm
A42: 40 | B42: 50 | C42: 25 | D42: 3 | E42: =(J42/G42)-C42 -> 2.709090909 | F42: 7 | G42: 11 | H42: =G42*F42 -> 77 | I42: 96 | J42: =(I42/8)*25.4 -> 304.8 | K42: =M42*J42/100 -> 1182.624 | L42: =(1000/H42)*(J42/1000)*M42/1000 -> 1.535875325 | M42: =( B42+D42)*F42+17 -> 388 | N42: Paper | O42: 013/040
A43: 41 | B43: 45 | C43: 124 | D43: 3 | E43: =(J43/G43)-C43 -> 3 | F43: 8 | G43: 3 | H43: =G43*F43 -> 24 | I43: 120 | J43: =(I43/8)*25.4 -> 381 | K43: =M43*J43/100 -> 1527.81 | L43: =(1000/H43)*(J43/1000)*M43/1000 -> 6.365875 | M43: =( B43+D43)*F43+17 -> 401 | N43: Paper | O43: 013/041
A44: 42 | B44: 80 | C44: 48 | D44: 3 | E44: =(J44/G44)-C44 -> 2.8 | F44: 5 | G44: 6 | H44: =G44*F44 -> 30 | I44: 96 | J44: =(I44/8)*25.4 -> 304.8 | K44: =M44*J44/100 -> 1316.736 | L44: =(1000/H44)*(J44/1000)*M44/1000 -> 4.38912 | M44: =( B44+D44)*F44+17 -> 432 | N44: Paper | O44: 013/042 | P44: Wink
A45: 43 | B45: 38 | C45: 136.7 | D45: 3 | E45: =(J45/G45)-C45 -> 3 | F45: 10 | G45: 4 | H45: =G45*F45 -> 40 | I45: 176 | J45: =(I45/8)*25.4 -> 558.8 | K45: =M45*J45/100 -> 2386.076 | L45: =(1000/H45)*(J45/1000)*M45/1000 -> 5.96519 | M45: =( B45+D45)*F45+17 -> 427 | N45: Paper | O45: 013/043 | P45: Wink
A46: 44 | B46: 88 | C46: 124 | D46: 3 | E46: =(J46/G46)-C46 -> 3 | F46: 2 | G46: 3 | H46: =G46*F46 -> 6 | I46: 120 | J46: =(I46/8)*25.4 -> 381 | K46: =M46*J46/100 -> 758.19 | L46: =(1000/H46)*(J46/1000)*M46/1000 -> 12.6365 | M46: =( B46+D46)*F46+17 -> 199 | N46: Paper | O46: 013/044 | P46: Wink-wadi food
A47: 45 | B47: 178 | C47: 148 | D47: 3 | E47: =(J47/G47)-C47 -> 3.341666667 | F47: 2 | G47: 3 | H47: =G47*F47 -> 6 | I47: 143 | J47: =(I47/8)*25.4 -> 454.025 | K47: =M47*J47/100 -> 1720.75475 | L47: =(1000/H47)*(J47/1000)*M47/1000 -> 28.67924583 | M47: =( B47+D47)*F47+17 -> 379 | N47: Paper | O47: 013/045
A48: 46 | B48: 50 | C48: 90 | D48: 3 | E48: =(J48/G48)-C48 -> 3.133333333 | F48: 7 | G48: 6 | H48: =G48*F48 -> 42 | I48: 176 | J48: =(I48/8)*25.4 -> 558.8 | K48: =M48*J48/100 -> 2168.144 | L48: =(1000/H48)*(J48/1000)*M48/1000 -> 5.162247619 | M48: =( B48+D48)*F48+17 -> 388 | N48: Paper | O48: 013/046
A49: 47 | B49: 255 | C49: 136 | D49: 3 | E49: =(J49/G49)-C49 -> 3.7 | F49: 1 | G49: 4 | H49: =G49*F49 -> 4 | I49: 176 | J49: =(I49/8)*25.4 -> 558.8 | K49: =M49*J49/100 -> 1536.7 | L49: =(1000/H49)*(J49/1000)*M49/1000 -> 38.4175 | M49: =( B49+D49)*F49+17 -> 275 | N49: Film | O49: 013/047 | P49: Front & back separated - Misr Petrolum 5L
A50: 48 | B50: 209 | C50: 137 | D50: 3 | E50: =(J50/G50)-C50 -> 2.7 | F50: 1 | G50: 4 | H50: =G50*F50 -> 4 | I50: 176 | J50: =(I50/8)*25.4 -> 558.8 | K50: =M50*J50/100 -> 1279.652 | L50: =(1000/H50)*(J50/1000)*M50/1000 -> 31.9913 | M50: =( B50+D50)*F50+17 -> 229 | N50: Film | O50: 013/048 | P50: Front & back separated - Misr Petrolum 4L
A51: 49 | B51: 152 | C51: 223 | D51: 3 | E51: =(J51/G51)-C51 -> 4.0125 | F51: 2 | G51: 2 | H51: =G51*F51 -> 4 | I51: 143 | J51: =(I51/8)*25.4 -> 454.025 | K51: =M51*J51/100 -> 1484.66175 | L51: =(1000/H51)*(J51/1000)*M51/1000 -> 37.11654375 | M51: =( B51+D51)*F51+17 -> 327 | N51: Film | O51: 013/049
A52: 50 | B52: 38 | C52: 130 | D52: 3 | E52: =(J52/G52)-C52 -> 3.35 | F52: 10 | G52: 3 | H52: =G52*F52 -> 30 | I52: 126 | J52: =(I52/8)*25.4 -> 400.05 | K52: =M52*J52/100 -> 1708.2135 | L52: =(1000/H52)*(J52/1000)*M52/1000 -> 5.694045 | M52: =( B52+D52)*F52+17 -> 427 | N52: Paper | O52: 013/050
A53: 51 | B53: 55 | C53: 180 | D53: 3 | E53: =(J53/G53)-C53 -> 6.266666667 | F53: 7 | G53: 3 | H53: =G53*F53 -> 21 | I53: 176 | J53: =(I53/8)*25.4 -> 558.8 | K53: =M53*J53/100 -> 2363.724 | L53: =(1000/H53)*(J53/1000)*M53/1000 -> 11.25582857 | M53: =( B53+D53)*F53+17 -> 423 | N53: Paper | O53: 013/051 | P53: El bwadi
A54: 52 | B54: 90 | C54: 159 | D54: 3 | E54: =(J54/G54)-C54 -> 2.925 | F54: 4 | G54: 2 | H54: =G54*F54 -> 8 | I54: 102 | J54: =(I54/8)*25.4 -> 323.85 | K54: =M54*J54/100 -> 1259.7765 | L54: =(1000/H54)*(J54/1000)*M54/1000 -> 15.74720625 | M54: =( B54+D54)*F54+17 -> 389 | N54: Paper | O54: 013/052 | P54: El bwadi
A55: 53 | B55: 40 | C55: 150 | D55: 3 | E55: =(J55/G55)-C55 -> 2.4 | F55: 8 | G55: 2 | H55: =G55*F55 -> 16 | I55: 96 | J55: =(I55/8)*25.4 -> 304.8 | K55: =M55*J55/100 -> 1100.328 | L55: =(1000/H55)*(J55/1000)*M55/1000 -> 6.87705 | M55: =( B55+D55)*F55+17 -> 361 | N55: Paper | O55: 013/053 | P55: El bwadi
A56: 54 | B56: 50 | C56: 187 | D56: 3 | E56: =(J56/G56)-C56 -> 3.5 | F56: 7 | G56: 2 | H56: =G56*F56 -> 14 | I56: 120 | J56: =(I56/8)*25.4 -> 381 | K56: =M56*J56/100 -> 1478.28 | L56: =(1000/H56)*(J56/1000)*M56/1000 -> 10.55914286 | M56: =( B56+D56)*F56+17 -> 388 | N56: Paper | O56: 013/054
A57: 55 | B57: 142 | C57: 60 | D57: 3 | E57: =(J57/G57)-C57 -> 3.5 | F57: 2 | G57: 6 | H57: =G57*F57 -> 12 | I57: 120 | J57: =(I57/8)*25.4 -> 381 | K57: =M57*J57/100 -> 1169.67 | L57: =(1000/H57)*(J57/1000)*M57/1000 -> 9.74725 | M57: =( B57+D57)*F57+17 -> 307 | N57: Film | O57: 013/055 | P57: Loreal
A58: 56 | B58: 106 | C58: 63 | D58: 3 | E58: =(J58/G58)-C58 -> 3.675 | F58: 2 | G58: 5 | H58: =G58*F58 -> 10 | I58: 105 | J58: =(I58/8)*25.4 -> 333.375 | K58: =M58*J58/100 -> 783.43125 | L58: =(1000/H58)*(J58/1000)*M58/1000 -> 7.8343125 | M58: =( B58+D58)*F58+17 -> 235 | N58: Paper | O58: 013/056 | P58: ADCO- Velvata front&back
A59: 57 | B59: 24 | C59: 14 | D59: 3 | E59: =(J59/G59)-C59 -> 2.933333333 | F59: 9 | G59: 18 | H59: =G59*F59 -> 162 | I59: 96 | J59: =(I59/8)*25.4 -> 304.8 | K59: =M59*J59/100 -> 792.48 | L59: =(1000/H59)*(J59/1000)*M59/1000 -> 0.4891851852 | M59: =( B59+D59)*F59+17 -> 260 | N59: Paper | O59: 013/057 | P59: Carmen
A60: 58 | B60: 147 | C60: 50 | D60: 3 | E60: =(J60/G60)-C60 -> 3.578125 | F60: 2 | G60: 8 | H60: =G60*F60 -> 16 | I60: 135 | J60: =(I60/8)*25.4 -> 428.625 | K60: =M60*J60/100 -> 1358.74125 | L60: =(1000/H60)*(J60/1000)*M60/1000 -> 8.492132813 | M60: =( B60+D60)*F60+17 -> 317 | N60: Film | O60: 013/058 | P60: Energy 1 ltr front&back
A61: 59 | B61: 70.5 | C61: 35.4 | D61: 3 | E61: =(J61/G61)-C61 -> 2.7 | F61: 5 | G61: 8 | H61: =G61*F61 -> 40 | I61: 96 | J61: =(I61/8)*25.4 -> 304.8 | K61: =M61*J61/100 -> 1171.956 | L61: =(1000/H61)*(J61/1000)*M61/1000 -> 2.92989 | M61: =( B61+D61)*F61+17 -> 384.5 | N61: Film | O61: 013/059 | P61: Vatika oil 45 ml
A62: 60 | B62: 78 | C62: 101 | D62: 3 | E62: =(J62/G62)-C62 -> 2.716666667 | F62: 4 | G62: 3 | H62: =G62*F62 -> 12 | I62: 98 | J62: =(I62/8)*25.4 -> 311.15 | K62: =M62*J62/100 -> 1061.0215 | L62: =(1000/H62)*(J62/1000)*M62/1000 -> 8.841845833 | M62: =( B62+D62)*F62+17 -> 341 | N62: Paper | O62: 013/060
A63: 61 | B63: 20 | C63: 50 | D63: 3 | E63: =(J63/G63)-C63 -> 3.578125 | F63: 18 | G63: 8 | H63: =G63*F63 -> 144 | I63: 135 | J63: =(I63/8)*25.4 -> 428.625 | K63: =M63*J63/100 -> 1847.37375 | L63: =(1000/H63)*(J63/1000)*M63/1000 -> 1.282898438 | M63: =( B63+D63)*F63+17 -> 431 | N63: Paper | O63: 013/061
A64: 62 | B64: 92 | C64: 124 | D64: 3 | E64: =(J64/G64)-C64 -> 3 | F64: 4 | G64: 3 | H64: =G64*F64 -> 12 | I64: 120 | J64: =(I64/8)*25.4 -> 381 | K64: =M64*J64/100 -> 1512.57 | L64: =(1000/H64)*(J64/1000)*M64/1000 -> 12.60475 | M64: =( B64+D64)*F64+17 -> 397 | N64: Paper | O64: 013/062
A65: 63 | B65: 150 | C65: 276 | D65: 3 | E65: =(J65/G65)-C65 -> 3.4 | F65: 2 | G65: 2 | H65: =G65*F65 -> 4 | I65: 176 | J65: =(I65/8)*25.4 -> 558.8 | K65: =M65*J65/100 -> 1804.924 | L65: =(1000/H65)*(J65/1000)*M65/1000 -> 45.1231 | M65: =( B65+D65)*F65+17 -> 323 | N65: Film | O65: 013/063
A66: 64 | B66: 100 | C66: 60 | D66: 3 | E66: =(J66/G66)-C66 -> 3.5 | F66: 4 | G66: 6 | H66: =G66*F66 -> 24 | I66: 120 | J66: =(I66/8)*25.4 -> 381 | K66: =M66*J66/100 -> 1634.49 | L66: =(1000/H66)*(J66/1000)*M66/1000 -> 6.810375 | M66: =( B66+D66)*F66+17 -> 429 | N66: Paper | O66: 013/064
A67: 65 | B67: 25 | C67: 555 | D67: 3 | E67: =(J67/G67)-C67 -> 3.8 | F67: 13 | G67: 1 | H67: =G67*F67 -> 13 | I67: 176 | J67: =(I67/8)*25.4 -> 558.8 | K67: =M67*J67/100 -> 2129.028 | L67: =(1000/H67)*(J67/1000)*M67/1000 -> 16.37713846 | M67: =( B67+D67)*F67+17 -> 381 | N67: Film | O67: 013/065
A68: 66 | B68: 70 | C68: 31 | D68: 3 | E68: =(J68/G68)-C68 -> 2.866666667 | F68: 5 | G68: 9 | H68: =G68*F68 -> 45 | I68: 96 | J68: =(I68/8)*25.4 -> 304.8 | K68: =M68*J68/100 -> 1164.336 | L68: =(1000/H68)*(J68/1000)*M68/1000 -> 2.587413333 | M68: =( B68+D68)*F68+17 -> 382 | N68: Film | O68: 013/066 | P68: italiano-el maleka
A69: 67 | B69: 67 | C69: 100 | D69: 3 | E69: =(J69/G69)-C69 -> 3.716666667 | F69: 3 | G69: 3 | H69: =G69*F69 -> 9 | I69: 98 | J69: =(I69/8)*25.4 -> 311.15 | K69: =M69*J69/100 -> 706.3105 | L69: =(1000/H69)*(J69/1000)*M69/1000 -> 7.847894444 | M69: =( B69+D69)*F69+17 -> 227 | N69: Film | O69: 013/067 | P69: Misr Petrolum
A70: 68 | B70: 30 | C70: 100 | D70: 3 | E70: =(J70/G70)-C70 -> 3.716666667 | F70: 8 | G70: 3 | H70: =G70*F70 -> 24 | I70: 98 | J70: =(I70/8)*25.4 -> 311.15 | K70: =M70*J70/100 -> 874.3315 | L70: =(1000/H70)*(J70/1000)*M70/1000 -> 3.643047917 | M70: =( B70+D70)*F70+17 -> 281 | N70: Paper | O70: 013/068
A71: 69 | B71: 62 | C71: 82 | D71: 3 | E71: =(J71/G71)-C71 -> 3.725 | F71: 6 | G71: 4 | H71: =G71*F71 -> 24 | I71: 108 | J71: =(I71/8)*25.4 -> 342.9 | K71: =M71*J71/100 -> 1395.603 | L71: =(1000/H71)*(J71/1000)*M71/1000 -> 5.8150125 | M71: =( B71+D71)*F71+17 -> 407 | N71: Paper | O71: 014/069
A72: 70 | B72: 51.5 | C72: 73 | D72: 3 | E72: =(J72/G72)-C72 -> 3.2 | F72: 7 | G72: 4 | H72: =G72*F72 -> 28 | I72: 96 | J72: =(I72/8)*25.4 -> 304.8 | K72: =M72*J72/100 -> 1214.628 | L72: =(1000/H72)*(J72/1000)*M72/1000 -> 4.337957143 | M72: =( B72+D72)*F72+17 -> 398.5 | N72: Paper | O72: 014/070
A73: 71 | B73: 121 | C73: 104 | D73: 3 | E73: =(J73/G73)-C73 -> 3.15625 | F73: 2 | G73: 4 | H73: =G73*F73 -> 8 | I73: 135 | J73: =(I73/8)*25.4 -> 428.625 | K73: =M73*J73/100 -> 1135.85625 | L73: =(1000/H73)*(J73/1000)*M73/1000 -> 14.19820313 | M73: =( B73+D73)*F73+17 -> 265 | N73: Paper | O73: 014/071 | P73: crystal 1.75 ltr same direcation
A74: 72 | B74: 40 | C74: 40 | D74: 3 | E74: =(J74/G74)-C74 -> 3.542857143 | F74: 8 | G74: 7 | H74: =G74*F74 -> 56 | I74: 96 | J74: =(I74/8)*25.4 -> 304.8 | K74: =M74*J74/100 -> 1100.328 | L74: =(1000/H74)*(J74/1000)*M74/1000 -> 1.964871429 | M74: =( B74+D74)*F74+17 -> 361 | N74: Paper | O74: 014/072
A75: 73 | B75: 125 | C75: 54 | D75: 3 | E75: =(J75/G75)-C75 -> 3.15 | F75: 3 | G75: 6 | H75: =G75*F75 -> 18 | I75: 108 | J75: =(I75/8)*25.4 -> 342.9 | K75: =M75*J75/100 -> 1375.029 | L75: =(1000/H75)*(J75/1000)*M75/1000 -> 7.63905 | M75: =( B75+D75)*F75+17 -> 401 | N75: Film | O75: 014/073 | P75: Loreal 200 ml
A76: 74 | B76: 35 | C76: 111 | D76: 3 | E76: =(J76/G76)-C76 -> 3.3 | F76: 10 | G76: 3 | H76: =G76*F76 -> 30 | I76: 108 | J76: =(I76/8)*25.4 -> 342.9 | K76: =M76*J76/100 -> 1361.313 | L76: =(1000/H76)*(J76/1000)*M76/1000 -> 4.53771 | M76: =( B76+D76)*F76+17 -> 397 | N76: Paper | O76: 014/074
A77: 75 | B77: 45 | C77: 149 | D77: 3 | E77: =(J77/G77)-C77 -> 3.4 | F77: 8 | G77: 2 | H77: =G77*F77 -> 16 | I77: 96 | J77: =(I77/8)*25.4 -> 304.8 | K77: =M77*J77/100 -> 1222.248 | L77: =(1000/H77)*(J77/1000)*M77/1000 -> 7.63905 | M77: =( B77+D77)*F77+17 -> 401 | N77: Paper | O77: 014/075 | P77: Fefe co small
A78: 76 | B78: 83 | C78: 159 | D78: 3 | E78: =(J78/G78)-C78 -> 2.925 | F78: 4 | G78: 2 | H78: =G78*F78 -> 8 | I78: 102 | J78: =(I78/8)*25.4 -> 323.85 | K78: =M78*J78/100 -> 1169.0985 | L78: =(1000/H78)*(J78/1000)*M78/1000 -> 14.61373125 | M78: =( B78+D78)*F78+17 -> 361 | N78: Paper | O78: 014/076 | P78: Fefe co big
A79: 77 | B79: 75 | C79: 84 | D79: 3 | E79: =(J79/G79)-C79 -> 6.805 | F79: 4 | G79: 5 | H79: =G79*F79 -> 20 | I79: 143 | J79: =(I79/8)*25.4 -> 454.025 | K79: =M79*J79/100 -> 1493.74225 | L79: =(1000/H79)*(J79/1000)*M79/1000 -> 7.46871125 | M79: =( B79+D79)*F79+17 -> 329 | N79: Film | O79: 014/077 | P79: peraly-natpack
A80: 78 | B80: 88 | C80: 330 | D80: 3 | E80: =(J80/G80)-C80 -> 3.375 | F80: 4 | G80: 1 | H80: =G80*F80 -> 4 | I80: 105 | J80: =(I80/8)*25.4 -> 333.375 | K80: =M80*J80/100 -> 1270.15875 | L80: =(1000/H80)*(J80/1000)*M80/1000 -> 31.75396875 | M80: =( B80+D80)*F80+17 -> 381 | N80: Film | O80: 014/078 | P80: Abu Hawa
A81: 79 | B81: 53 | C81: 340 | D81: 3 | E81: =(J81/G81)-C81 -> 2.9 | F81: 6 | G81: 1 | H81: =G81*F81 -> 6 | I81: 108 | J81: =(I81/8)*25.4 -> 342.9 | K81: =M81*J81/100 -> 1210.437 | L81: =(1000/H81)*(J81/1000)*M81/1000 -> 20.17395 | M81: =( B81+D81)*F81+17 -> 353 | N81: Film | O81: 014/079 | P81: Abu Hawa
A82: 80 | B82: 58 | C82: 340 | D82: 3 | E82: =(J82/G82)-C82 -> 2.9 | F82: 6 | G82: 1 | H82: =G82*F82 -> 6 | I82: 108 | J82: =(I82/8)*25.4 -> 342.9 | K82: =M82*J82/100 -> 1313.307 | L82: =(1000/H82)*(J82/1000)*M82/1000 -> 21.88845 | M82: =( B82+D82)*F82+17 -> 383 | N82: Film | O82: 014/080 | P82: Abu Hawa
A83: 81 | B83: 16 | C83: 320 | D83: 3 | E83: =(J83/G83)-C83 -> 3.85 | F83: 16 | G83: 1 | H83: =G83*F83 -> 16 | I83: 102 | J83: =(I83/8)*25.4 -> 323.85 | K83: =M83*J83/100 -> 1039.5585 | L83: =(1000/H83)*(J83/1000)*M83/1000 -> 6.497240625 | M83: =( B83+D83)*F83+17 -> 321 | N83: Film | O83: 014/081 | P83: Abu Hawa
A84: 82 | B84: 34.5 | C84: 340 | D84: 3 | E84: =(J84/G84)-C84 -> 2.9 | F84: 10 | G84: 1 | H84: =G84*F84 -> 10 | I84: 108 | J84: =(I84/8)*25.4 -> 342.9 | K84: =M84*J84/100 -> 1344.168 | L84: =(1000/H84)*(J84/1000)*M84/1000 -> 13.44168 | M84: =( B84+D84)*F84+17 -> 392 | N84: Film | O84: 014/082 | P84: Abu Hawa
A85: 83 | B85: 108 | C85: 340 | D85: 3 | E85: =(J85/G85)-C85 -> 2.9 | F85: 2 | G85: 1 | H85: =G85*F85 -> 2 | I85: 108 | J85: =(I85/8)*25.4 -> 342.9 | K85: =M85*J85/100 -> 819.531 | L85: =(1000/H85)*(J85/1000)*M85/1000 -> 40.97655 | M85: =( B85+D85)*F85+17 -> 239 | N85: Film | O85: 014/083 | P85: Abu Hawa-jumpo
A86: 84 | B86: 53 | C86: 451 | D86: 3 | E86: =(J86/G86)-C86 -> 3.025 | F86: 6 | G86: 1 | H86: =G86*F86 -> 6 | I86: 143 | J86: =(I86/8)*25.4 -> 454.025 | K86: =M86*J86/100 -> 1602.70825 | L86: =(1000/H86)*(J86/1000)*M86/1000 -> 26.71180417 | M86: =( B86+D86)*F86+17 -> 353 | N86: Film | O86: 014/084 | P86: Abu Hawa
A87: 85 | B87: 11 | C87: 426 | D87: 3 | E87: =(J87/G87)-C87 -> 2.625 | F87: 20 | G87: 1 | H87: =G87*F87 -> 20 | I87: 135 | J87: =(I87/8)*25.4 -> 428.625 | K87: =M87*J87/100 -> 1273.01625 | L87: =(1000/H87)*(J87/1000)*M87/1000 -> 6.36508125 | M87: =( B87+D87)*F87+17 -> 297 | N87: Film | O87: 014/085 | P87: Abu Hawa
A88: 86 | B88: 125.5 | C88: 183 | D88: 3 | E88: =(J88/G88)-C88 -> 3.266666667 | F88: 3 | G88: 3 | H88: =G88*F88 -> 9 | I88: 176 | J88: =(I88/8)*25.4 -> 558.8 | K88: =M88*J88/100 -> 2249.17 | L88: =(1000/H88)*(J88/1000)*M88/1000 -> 24.99077778 | M88: =( B88+D88)*F88+17 -> 402.5 | N88: Film | O88: 014/086 | P88: el bwadi-bigعلوي
A89: 87 | B89: 51 | C89: 183 | D89: 3 | E89: =(J89/G89)-C89 -> 3.266666667 | F89: 7 | G89: 3 | H89: =G89*F89 -> 21 | I89: 176 | J89: =(I89/8)*25.4 -> 558.8 | K89: =M89*J89/100 -> 2207.26 | L89: =(1000/H89)*(J89/1000)*M89/1000 -> 10.5107619 | M89: =( B89+D89)*F89+17 -> 395 | N89: Paper | O89: 014/087 | P89: WadiFood- Olives export 115-320
A90: 88 | B90: 60 | C90: 124 | D90: 3 | E90: =(J90/G90)-C90 -> 3 | F90: 6 | G90: 3 | H90: =G90*F90 -> 18 | I90: 120 | J90: =(I90/8)*25.4 -> 381 | K90: =M90*J90/100 -> 1504.95 | L90: =(1000/H90)*(J90/1000)*M90/1000 -> 8.360833333 | M90: =( B90+D90)*F90+17 -> 395 | N90: Paper | O90: 014/088
A91: 89 | B91: 94 | C91: 48 | D91: 3 | E91: =(J91/G91)-C91 -> 2.8 | F91: 4 | G91: 6 | H91: =G91*F91 -> 24 | I91: 96 | J91: =(I91/8)*25.4 -> 304.8 | K91: =M91*J91/100 -> 1234.44 | L91: =(1000/H91)*(J91/1000)*M91/1000 -> 5.1435 | M91: =( B91+D91)*F91+17 -> 405 | N91: Film | O91: 014/89 | P91: LOREAL-ULTRA DUX 90 ML
A92: 90 | B92: 64 | C92: 30 | D92: 3 | E92: =(J92/G92)-C92 -> 3.3375 | F92: 6 | G92: 10 | H92: =G92*F92 -> 60 | I92: 105 | J92: =(I92/8)*25.4 -> 333.375 | K92: =M92*J92/100 -> 1396.84125 | L92: =(1000/H92)*(J92/1000)*M92/1000 -> 2.32806875 | M92: =( B92+D92)*F92+17 -> 419 | N92: Film | O92: 014/090 | P92: EVA front&back AleoVera 50
A93: 91 | B93: 70 | C93: 36 | D93: 3 | E93: =(J93/G93)-C93 -> 2.89375 | F93: 5 | G93: 8 | H93: =G93*F93 -> 40 | I93: 98 | J93: =(I93/8)*25.4 -> 311.15 | K93: =M93*J93/100 -> 1188.593 | L93: =(1000/H93)*(J93/1000)*M93/1000 -> 2.9714825 | M93: =( B93+D93)*F93+17 -> 382 | N93: Film | O93: 014/091 | P93: El Melaka open label
A94: 92 | B94: 40 | C94: 100 | D94: 3 | E94: =(J94/G94)-C94 -> 3.716666667 | F94: 8 | G94: 3 | H94: =G94*F94 -> 24 | I94: 98 | J94: =(I94/8)*25.4 -> 311.15 | K94: =M94*J94/100 -> 1123.2515 | L94: =(1000/H94)*(J94/1000)*M94/1000 -> 4.680214583 | M94: =( B94+D94)*F94+17 -> 361 | N94: Paper | O94: 014/092
A95: 93 | B95: 44 | C95: 105 | D95: 3 | E95: =(J95/G95)-C95 -> 2.95 | F95: 8 | G95: 3 | H95: =G95*F95 -> 24 | I95: 102 | J95: =(I95/8)*25.4 -> 323.85 | K95: =M95*J95/100 -> 1272.7305 | L95: =(1000/H95)*(J95/1000)*M95/1000 -> 5.30304375 | M95: =( B95+D95)*F95+17 -> 393 | N95: Paper | O95: 014/093
A96: 94 | B96: 89 | C96: 39 | D96: 3 | E96: =(J96/G96)-C96 -> 2.671875 | F96: 4 | G96: 8 | H96: =G96*F96 -> 32 | I96: 105 | J96: =(I96/8)*25.4 -> 333.375 | K96: =M96*J96/100 -> 1283.49375 | L96: =(1000/H96)*(J96/1000)*M96/1000 -> 4.010917969 | M96: =( B96+D96)*F96+17 -> 385 | N96: Film | O96: 014/094 | P96: EVA front&back AleoVera 100
A97: 95 | B97: 140 | C97: 60 | D97: 3 | E97: =(J97/G97)-C97 -> 3.5 | F97: 2 | G97: 6 | H97: =G97*F97 -> 12 | I97: 120 | J97: =(I97/8)*25.4 -> 381 | K97: =M97*J97/100 -> 1154.43 | L97: =(1000/H97)*(J97/1000)*M97/1000 -> 9.62025 | M97: =( B97+D97)*F97+17 -> 303 | N97: Film | O97: 014/095 | P97: EVA front&back AleoVera 300
A98: 96 | B98: 50 | C98: 73 | D98: 3 | E98: =(J98/G98)-C98 -> 3.2 | F98: 7 | G98: 4 | H98: =G98*F98 -> 28 | I98: 96 | J98: =(I98/8)*25.4 -> 304.8 | K98: =M98*J98/100 -> 1182.624 | L98: =(1000/H98)*(J98/1000)*M98/1000 -> 4.223657143 | M98: =( B98+D98)*F98+17 -> 388 | N98: Paper | O98: 014/096
A99: 97 | B99: 73 | C99: 140 | D99: 3 | E99: =(J99/G99)-C99 -> 2.875 | F99: 5 | G99: 3 | H99: =G99*F99 -> 15 | I99: 135 | J99: =(I99/8)*25.4 -> 428.625 | K99: =M99*J99/100 -> 1701.64125 | L99: =(1000/H99)*(J99/1000)*M99/1000 -> 11.344275 | M99: =( B99+D99)*F99+17 -> 397 | N99: Paper | O99: 014/097
A100: 98 | B100: 85 | C100: 41.5 | D100: 3 | E100: =(J100/G100)-C100 -> 2.95 | F100: 4 | G100: 7 | H100: =G100*F100 -> 28 | I100: 98 | J100: =(I100/8)*25.4 -> 311.15 | K100: =M100*J100/100 -> 1148.1435 | L100: =(1000/H100)*(J100/1000)*M100/1000 -> 4.1005125 | M100: =( B100+D100)*F100+17 -> 369 | N100: Paper | O100: 014/098
...

Sheet LEGACY_REVISION
C3: WANTED LABELS | E3: DIE NO. | F3: TOTAL NO FROM DIE | G3: CYLINDER | H3: REPEAT | I3: MATERIAL | J3: COLOR | K3: AFTER COLOR | L3: REEL | M3: NO. OF REELS | N3: FOR REEL | O3: TOTAL
C4: 100000 | E4: 1844 | F4: #N/A | G4: #N/A | H4: =(G4*3.175)/1000 -> #N/A | I4: =C4/F4*H4 -> #N/A | J4: 7 | K4: =I4+(50*J4) -> #N/A | L4: 2000 | M4: =K4/L4 -> #N/A | N4: =M4*50 -> #N/A | O4: =K4+N4 -> #N/A | R4: 50
C7: MATERIAL | E7: LABEL WIDTH | F7: NO. ACROSS | G7: MATERIAL WIDTH | H7: MATERIAL P&S
E8: 91.65 | F8: 3 | G8: =(E8+3)*F8+17 -> 300.95 | H8: =G8+20 -> 320.95
C10: MIN GAP | E10: LABEL LENGTH | F10: CYLINDER | G10: REPEAT | H10: REPEAT L N | I10: MIN GAP
E11: 125.119 | F11: 84 | G11: =F11*3.175 -> 266.7 | H11: =G11/(E11+2.4) -> 2.091453038 | I11: =((H11)-TRUNC(H11))*(E11+2.4)/TRUNC(H11)+2.4 -> 8.231
E13: =E11 -> 125.119 | F13: 86 | G13: =F13*3.175 -> 273.05 | H13: =G13/(E13+2.4) -> 2.141249539 | I13: =((H13)-TRUNC(H13))*(E13+2.4)/TRUNC(H13)+2.4 -> 11.406
E15: =E11 -> 125.119 | F15: 88 | G15: =F15*3.175 -> 279.4 | H15: =G15/(E15+2.4) -> 2.19104604 | I15: =((H15)-TRUNC(H15))*(E15+2.4)/TRUNC(H15)+2.4 -> 14.581
E17: =E11 -> 125.119 | F17: 90 | G17: =F17*3.175 -> 285.75 | H17: =G17/(E17+2.4) -> 2.240842541 | I17: =((H17)-TRUNC(H17))*(E17+2.4)/TRUNC(H17)+2.4 -> 17.756
E19: =E11 -> 125.119 | F19: 96 | G19: =F19*3.175 -> 304.8 | H19: =G19/(E19+2.4) -> 2.390232044 | I19: =((H19)-TRUNC(H19))*(E19+2.4)/TRUNC(H19)+2.4 -> 27.281
E21: =E11 -> 125.119 | F21: 98 | G21: =F21*3.175 -> 311.15 | H21: =G21/(E21+2.4) -> 2.440028545 | I21: =((H21)-TRUNC(H21))*(E21+2.4)/TRUNC(H21)+2.4 -> 30.456
E23: =E11 -> 125.119 | F23: 102 | G23: =F23*3.175 -> 323.85 | H23: =G23/(E23+2.4) -> 2.539621547 | I23: =((H23)-TRUNC(H23))*(E23+2.4)/TRUNC(H23)+2.4 -> 36.806
E25: =E13 -> 125.119 | F25: 105 | G25: =F25*3.175 -> 333.375 | H25: =G25/(E25+2.4) -> 2.614316298 | I25: =((H25)-TRUNC(H25))*(E25+2.4)/TRUNC(H25)+2.4 -> 41.5685
E27: =E17 -> 125.119 | F27: 108 | G27: =F27*3.175 -> 342.9 | H27: =G27/(E27+2.4) -> 2.689011049 | I27: =((H27)-TRUNC(H27))*(E27+2.4)/TRUNC(H27)+2.4 -> 46.331
E29: =E17 -> 125.119 | F29: 110 | G29: =F29*3.175 -> 349.25 | H29: =G29/(E29+2.4) -> 2.73880755 | I29: =((H29)-TRUNC(H29))*(E29+2.4)/TRUNC(H29)+2.4 -> 49.506
E31: =E19 -> 125.119 | F31: 120 | G31: =F31*3.175 -> 381 | H31: =G31/(E31+2.4) -> 2.987790055 | I31: =((H31)-TRUNC(H31))*(E31+2.4)/TRUNC(H31)+2.4 -> 65.381
E33: =E21 -> 125.119 | F33: 126 | G33: =F33*3.175 -> 400.05 | H33: =G33/(E33+2.4) -> 3.137179558 | I33: =((H33)-TRUNC(H33))*(E33+2.4)/TRUNC(H33)+2.4 -> 8.231
E35: =E23 -> 125.119 | F35: 128 | G35: =F35*3.175 -> 406.4 | H35: =G35/(E35+2.4) -> 3.186976058 | I35: =((H35)-TRUNC(H35))*(E35+2.4)/TRUNC(H35)+2.4 -> 10.34766667
E37: =E23 -> 125.119 | F37: 132 | G37: =F37*3.175 -> 419.1 | H37: =G37/(E37+2.4) -> 3.28656906 | I37: =((H37)-TRUNC(H37))*(E37+2.4)/TRUNC(H37)+2.4 -> 14.581
E39: =E25 -> 125.119 | F39: 135 | G39: =F39*3.175 -> 428.625 | H39: =G39/(E39+2.4) -> 3.361263812 | I39: =((H39)-TRUNC(H39))*(E39+2.4)/TRUNC(H39)+2.4 -> 17.756
E41: =E29 -> 125.119 | F41: 143 | G41: =F41*3.175 -> 454.025 | H41: =G41/(E41+2.4) -> 3.560449815 | I41: =((H41)-TRUNC(H41))*(E41+2.4)/TRUNC(H41)+2.4 -> 26.22266667
E43: =E31 -> 125.119 | F43: 148 | G43: =F43*3.175 -> 469.9 | H43: =G43/(E43+2.4) -> 3.684941068 | I43: =((H43)-TRUNC(H43))*(E43+2.4)/TRUNC(H43)+2.4 -> 31.51433333
E45: =E33 -> 125.119 | F45: 153 | G45: =F45*3.175 -> 485.775 | H45: =G45/(E45+2.4) -> 3.80943232 | I45: =((H45)-TRUNC(H45))*(E45+2.4)/TRUNC(H45)+2.4 -> 36.806
E47: =E37 -> 125.119 | F47: 165 | G47: =F47*3.175 -> 523.875 | H47: =G47/(E47+2.4) -> 4.108211325 | I47: =((H47)-TRUNC(H47))*(E47+2.4)/TRUNC(H47)+2.4 -> 5.84975
E49: =E39 -> 125.119 | F49: 176 | G49: =F49*3.175 -> 558.8 | H49: =G49/(E49+2.4) -> 4.38209208 | I49: =((H49)-TRUNC(H49))*(E49+2.4)/TRUNC(H49)+2.4 -> 14.581
E51: =E41 -> 125.119 | F51: 128 | G51: =F51*3.175 -> 406.4 | H51: =G51/(E51+2.4) -> 3.186976058 | I51: =((H51)-TRUNC(H51))*(E51+2.4)/TRUNC(H51)+2.4 -> 10.34766667
F54: =450+100 -> 550 | G54: 200 | H54: 2177 | I54: 150
D56: الكمية المطلوبة | E56: مقاس الليبل | F56: الجاب | G56: التكرار | H56: =(H57*1000)/3.175 -> 153 | J56: الصافي المطلوب | K56: عدد الألوان | L56: البكر المطلوب | M56: الكمية الكلية
C57: CYLINDER | D57: 100000 | E57: 159 | F57: 2.925 | G57: 3 | H57: =(E57+F57)*G57/1000 -> 0.485775 | I57: التكرار بالمتر | J57: =D57/(G57*G58)*H57 -> 4048.125 | K57: 4 | L57: =(J57+(K57*50))/2000 -> 2.1240625 | M57: =J57+(K57*50)+L58*50 -> 4354.625 | N57: متر طولي | P57: سعر المتر المربع | Q57: سعر اللون للمتر المربع
C58: WIDTH | E58: 90 | F58: 3 | G58: 4 | H58: 390 | I58: عرض الخامة | J58: 390 | L58: =ROUNDUP(L57,L57) -> 2.13 | M58: =M57*(H58/1000) -> 1698.30375 | N58: متر مربع حقيقي | P58: 8 | Q58: 9 | S58: الربح في المتر
M59: =M57*(H58/1000)+(M57*((J58-H58)/1000)) -> 1698.30375 | N59: زيادة | S59: 2 | T59: =M58*S59+M58*S61*K57 -> 6793.215 | U59: =100/T59 -> 0.01472057045
M60: =M58*P58+M58*K57*Q58 -> 74725.365 | N60: سعر حقيقي | S60: الربح في اللون | T60: =M59*S59+M59*S61*K57 -> 6793.215 | U60: =100/T60 -> 0.01472057045
M61: =M59*P58+M59*K57*Q58 -> 74725.365 | N61: سعر زيادة | S61: 0.5 | U61: =U60-U59 -> 0

Sheet CYLINDER_SELECTOR
A1: CYLINDER / REPEAT SELECTOR
A3: CYLINDER CANDIDATE ANALYSIS
A4: Cylinder Teeth | B4: Repeat (mm) | C4: Label Length (mm) | D4: Min Gap Target | E4: Labels Around | F4: Actual Gap Around | G4: Gap Status | H4: Repeat Utilization % | I4: Material / Machine | J4: Compatibility | K4: Score | L4: Recommendation
A5: 80 | B5: =A5*3.175 -> 254 | C5: =JOB_INPUTS!B10 -> 90 | D5: =JOB_INPUTS!B13 -> 2.5 | E5: =INT(B5/(C5+D5)) -> 2 | F5: =IF(E5>0,(B5/E5)-C5,"") -> 37 | G5: =IF(F5>5,"GAP TOO BIG",IF(F5>=D5,"OK","GAP TOO SMALL")) -> GAP TOO BIG | H5: =IF(B5>0,E5*(C5+F5)/B5,"") -> 1 | I5: NARROW WEB | J5: =IF(AND(E5>=1,F5>=D5),"COMPATIBLE","NOT COMPATIBLE") -> COMPATIBLE | K5: =IF(J5="COMPATIBLE",F5*100+E5*10+H5*10,0) -> 3730 | L5: =IF(AND(J5="COMPATIBLE",K5=MIN($K$5:$K$17)),"BEST OPTION","")
A6: 88 | B6: =A6*3.175 -> 279.4 | C6: =JOB_INPUTS!B10 -> 90 | D6: =JOB_INPUTS!B13 -> 2.5 | E6: =INT(B6/(C6+D6)) -> 3 | F6: =IF(E6>0,(B6/E6)-C6,"") -> 3.133333333 | G6: =IF(F6>5,"GAP TOO BIG",IF(F6>=D6,"OK","GAP TOO SMALL")) -> OK | H6: =IF(B6>0,E6*(C6+F6)/B6,"") -> 1 | I6: NARROW WEB | J6: =IF(AND(E6>=1,F6>=D6),"COMPATIBLE","NOT COMPATIBLE") -> COMPATIBLE | K6: =IF(J6="COMPATIBLE",F6*100+E6*10+H6*10,0) -> 353.3333333 | L6: =IF(AND(J6="COMPATIBLE",K6=MIN($K$5:$K$17)),"BEST OPTION","")
A7: 90 | B7: =A7*3.175 -> 285.75 | C7: =JOB_INPUTS!B10 -> 90 | D7: =JOB_INPUTS!B13 -> 2.5 | E7: =INT(B7/(C7+D7)) -> 3 | F7: =IF(E7>0,(B7/E7)-C7,"") -> 5.25 | G7: =IF(F7>5,"GAP TOO BIG",IF(F7>=D7,"OK","GAP TOO SMALL")) -> GAP TOO BIG | H7: =IF(B7>0,E7*(C7+F7)/B7,"") -> 1 | I7: NARROW WEB | J7: =IF(AND(E7>=1,F7>=D7),"COMPATIBLE","NOT COMPATIBLE") -> COMPATIBLE | K7: =IF(J7="COMPATIBLE",F7*100+E7*10+H7*10,0) -> 565 | L7: =IF(AND(J7="COMPATIBLE",K7=MIN($K$5:$K$17)),"BEST OPTION","")
A8: 98 | B8: =A8*3.175 -> 311.15 | C8: =JOB_INPUTS!B10 -> 90 | D8: =JOB_INPUTS!B13 -> 2.5 | E8: =INT(B8/(C8+D8)) -> 3 | F8: =IF(E8>0,(B8/E8)-C8,"") -> 13.71666667 | G8: =IF(F8>5,"GAP TOO BIG",IF(F8>=D8,"OK","GAP TOO SMALL")) -> GAP TOO BIG | H8: =IF(B8>0,E8*(C8+F8)/B8,"") -> 1 | I8: NARROW WEB | J8: =IF(AND(E8>=1,F8>=D8),"COMPATIBLE","NOT COMPATIBLE") -> COMPATIBLE | K8: =IF(J8="COMPATIBLE",F8*100+E8*10+H8*10,0) -> 1411.666667 | L8: =IF(AND(J8="COMPATIBLE",K8=MIN($K$5:$K$17)),"BEST OPTION","")
A9: 106 | B9: =A9*3.175 -> 336.55 | C9: =JOB_INPUTS!B10 -> 90 | D9: =JOB_INPUTS!B13 -> 2.5 | E9: =INT(B9/(C9+D9)) -> 3 | F9: =IF(E9>0,(B9/E9)-C9,"") -> 22.18333333 | G9: =IF(F9>5,"GAP TOO BIG",IF(F9>=D9,"OK","GAP TOO SMALL")) -> GAP TOO BIG | H9: =IF(B9>0,E9*(C9+F9)/B9,"") -> 1 | I9: NARROW WEB | J9: =IF(AND(E9>=1,F9>=D9),"COMPATIBLE","NOT COMPATIBLE") -> COMPATIBLE | K9: =IF(J9="COMPATIBLE",F9*100+E9*10+H9*10,0) -> 2258.333333 | L9: =IF(AND(J9="COMPATIBLE",K9=MIN($K$5:$K$17)),"BEST OPTION","")
A10: 111 | B10: =A10*3.175 -> 352.425 | C10: =JOB_INPUTS!B10 -> 90 | D10: =JOB_INPUTS!B13 -> 2.5 | E10: =INT(B10/(C10+D10)) -> 3 | F10: =IF(E10>0,(B10/E10)-C10,"") -> 27.475 | G10: =IF(F10>5,"GAP TOO BIG",IF(F10>=D10,"OK","GAP TOO SMALL")) -> GAP TOO BIG | H10: =IF(B10>0,E10*(C10+F10)/B10,"") -> 1 | I10: NARROW WEB | J10: =IF(AND(E10>=1,F10>=D10),"COMPATIBLE","NOT COMPATIBLE") -> COMPATIBLE | K10: =IF(J10="COMPATIBLE",F10*100+E10*10+H10*10,0) -> 2787.5 | L10: =IF(AND(J10="COMPATIBLE",K10=MIN($K$5:$K$17)),"BEST OPTION","")
A11: 117 | B11: =A11*3.175 -> 371.475 | C11: =JOB_INPUTS!B10 -> 90 | D11: =JOB_INPUTS!B13 -> 2.5 | E11: =INT(B11/(C11+D11)) -> 4 | F11: =IF(E11>0,(B11/E11)-C11,"") -> 2.86875 | G11: =IF(F11>5,"GAP TOO BIG",IF(F11>=D11,"OK","GAP TOO SMALL")) -> OK | H11: =IF(B11>0,E11*(C11+F11)/B11,"") -> 1 | I11: NARROW WEB | J11: =IF(AND(E11>=1,F11>=D11),"COMPATIBLE","NOT COMPATIBLE") -> COMPATIBLE | K11: =IF(J11="COMPATIBLE",F11*100+E11*10+H11*10,0) -> 336.875 | L11: =IF(AND(J11="COMPATIBLE",K11=MIN($K$5:$K$17)),"BEST OPTION","") -> BEST OPTION
A12: 124 | B12: =A12*3.175 -> 393.7 | C12: =JOB_INPUTS!B10 -> 90 | D12: =JOB_INPUTS!B13 -> 2.5 | E12: =INT(B12/(C12+D12)) -> 4 | F12: =IF(E12>0,(B12/E12)-C12,"") -> 8.425 | G12: =IF(F12>5,"GAP TOO BIG",IF(F12>=D12,"OK","GAP TOO SMALL")) -> GAP TOO BIG | H12: =IF(B12>0,E12*(C12+F12)/B12,"") -> 1 | I12: NARROW WEB | J12: =IF(AND(E12>=1,F12>=D12),"COMPATIBLE","NOT COMPATIBLE") -> COMPATIBLE | K12: =IF(J12="COMPATIBLE",F12*100+E12*10+H12*10,0) -> 892.5 | L12: =IF(AND(J12="COMPATIBLE",K12=MIN($K$5:$K$17)),"BEST OPTION","")
A13: 135 | B13: =A13*3.175 -> 428.625 | C13: =JOB_INPUTS!B10 -> 90 | D13: =JOB_INPUTS!B13 -> 2.5 | E13: =INT(B13/(C13+D13)) -> 4 | F13: =IF(E13>0,(B13/E13)-C13,"") -> 17.15625 | G13: =IF(F13>5,"GAP TOO BIG",IF(F13>=D13,"OK","GAP TOO SMALL")) -> GAP TOO BIG | H13: =IF(B13>0,E13*(C13+F13)/B13,"") -> 1 | I13: NARROW WEB | J13: =IF(AND(E13>=1,F13>=D13),"COMPATIBLE","NOT COMPATIBLE") -> COMPATIBLE | K13: =IF(J13="COMPATIBLE",F13*100+E13*10+H13*10,0) -> 1765.625 | L13: =IF(AND(J13="COMPATIBLE",K13=MIN($K$5:$K$17)),"BEST OPTION","")
A14: 149 | B14: =A14*3.175 -> 473.075 | C14: =JOB_INPUTS!B10 -> 90 | D14: =JOB_INPUTS!B13 -> 2.5 | E14: =INT(B14/(C14+D14)) -> 5 | F14: =IF(E14>0,(B14/E14)-C14,"") -> 4.615 | G14: =IF(F14>5,"GAP TOO BIG",IF(F14>=D14,"OK","GAP TOO SMALL")) -> OK | H14: =IF(B14>0,E14*(C14+F14)/B14,"") -> 1 | I14: NARROW WEB | J14: =IF(AND(E14>=1,F14>=D14),"COMPATIBLE","NOT COMPATIBLE") -> COMPATIBLE | K14: =IF(J14="COMPATIBLE",F14*100+E14*10+H14*10,0) -> 521.5 | L14: =IF(AND(J14="COMPATIBLE",K14=MIN($K$5:$K$17)),"BEST OPTION","")
A15: 154 | B15: =A15*3.175 -> 488.95 | C15: =JOB_INPUTS!B10 -> 90 | D15: =JOB_INPUTS!B13 -> 2.5 | E15: =INT(B15/(C15+D15)) -> 5 | F15: =IF(E15>0,(B15/E15)-C15,"") -> 7.79 | G15: =IF(F15>5,"GAP TOO BIG",IF(F15>=D15,"OK","GAP TOO SMALL")) -> GAP TOO BIG | H15: =IF(B15>0,E15*(C15+F15)/B15,"") -> 1 | I15: NARROW WEB | J15: =IF(AND(E15>=1,F15>=D15),"COMPATIBLE","NOT COMPATIBLE") -> COMPATIBLE | K15: =IF(J15="COMPATIBLE",F15*100+E15*10+H15*10,0) -> 839 | L15: =IF(AND(J15="COMPATIBLE",K15=MIN($K$5:$K$17)),"BEST OPTION","")
A16: 160 | B16: =A16*3.175 -> 508 | C16: =JOB_INPUTS!B10 -> 90 | D16: =JOB_INPUTS!B13 -> 2.5 | E16: =INT(B16/(C16+D16)) -> 5 | F16: =IF(E16>0,(B16/E16)-C16,"") -> 11.6 | G16: =IF(F16>5,"GAP TOO BIG",IF(F16>=D16,"OK","GAP TOO SMALL")) -> GAP TOO BIG | H16: =IF(B16>0,E16*(C16+F16)/B16,"") -> 1 | I16: NARROW WEB | J16: =IF(AND(E16>=1,F16>=D16),"COMPATIBLE","NOT COMPATIBLE") -> COMPATIBLE | K16: =IF(J16="COMPATIBLE",F16*100+E16*10+H16*10,0) -> 1220 | L16: =IF(AND(J16="COMPATIBLE",K16=MIN($K$5:$K$17)),"BEST OPTION","")
A17: 189 | B17: =A17*3.175 -> 600.075 | C17: =JOB_INPUTS!B10 -> 90 | D17: =JOB_INPUTS!B13 -> 2.5 | E17: =INT(B17/(C17+D17)) -> 6 | F17: =IF(E17>0,(B17/E17)-C17,"") -> 10.0125 | G17: =IF(F17>5,"GAP TOO BIG",IF(F17>=D17,"OK","GAP TOO SMALL")) -> GAP TOO BIG | H17: =IF(B17>0,E17*(C17+F17)/B17,"") -> 1 | I17: NARROW WEB | J17: =IF(AND(E17>=1,F17>=D17),"COMPATIBLE","NOT COMPATIBLE") -> COMPATIBLE | K17: =IF(J17="COMPATIBLE",F17*100+E17*10+H17*10,0) -> 1071.25 | L17: =IF(AND(J17="COMPATIBLE",K17=MIN($K$5:$K$17)),"BEST OPTION","")
A20: SELECTED CYLINDER RESULT
A21: Recommended Cylinder Teeth | B21: {=INDEX(A5:A17,MATCH(MIN(K5:K17),K5:K17,0))} -> 117
A22: Recommended Repeat | B22: {=INDEX(B5:B17,MATCH(MIN(K5:K17),K5:K17,0))} -> 371.475
A23: Labels Around | B23: {=INDEX(E5:E17,MATCH(MIN(K5:K17),K5:K17,0))} -> 4
A24: Actual Gap Around | B24: {=INDEX(F5:F17,MATCH(MIN(K5:K17),K5:K17,0))} -> 2.86875
A25: Compatibility | B25: {=INDEX(J5:J17,MATCH(MIN(K5:K17),K5:K17,0))} -> COMPATIBLE
